README.rst
setup.py
abo/__init__.py
abo/generator.py
abo/transaction.py
abo_generator.egg-info/PKG-INFO
abo_generator.egg-info/SOURCES.txt
abo_generator.egg-info/dependency_links.txt
abo_generator.egg-info/top_level.txt