Metadata-Version: 1.1
Name: abo-generator
Version: 0.2.2
Summary: ABO banking format generator
Home-page: UNKNOWN
Author: Viktor Stískala
Author-email: viktor@stiskala.cz
License: MPL
Platform: UNKNOWN
Classifier: Intended Audience :: Developers
Classifier: Operating System :: OS Independent
Classifier: Programming Language :: Python
Classifier: Programming Language :: Python :: 3.3
Classifier: Topic :: Software Development :: Libraries
Classifier: Topic :: Software Development :: Libraries :: Python Modules
